rssgen/__init__.py
rssgen/__main__.py
rssgen/compat.py
rssgen/entry.py
rssgen/feed.py
rssgen/util.py
rssgen/version.py
rssgen-0.9.0.dist-info/METADATA
rssgen-0.9.0.dist-info/WHEEL
rssgen-0.9.0.dist-info/top_level.txt
rssgen-0.9.0.dist-info/RECORD
