Metadata-Version: 2.1
Name: rssgen
Version: 0.9.0
Summary: RSS Generator
Home-page: https://github.com/mstg/rssgen
Author: Mustafa Gezen
Author-email: mustafa@gezen.no
License: FreeBSD and LGPLv3+
Keywords: RSS
Classifier: Development Status :: 5 - Production/Stable
Classifier: Intended Audience :: Developers
Classifier: Intended Audience :: Information Technology
Classifier: Intended Audience :: Science/Research
Classifier: License :: OSI Approved :: BSD License
Classifier: License :: OSI Approved :: GNU Lesser General Public License v3 or later (LGPLv3+)
Classifier: Natural Language :: English
Classifier: Operating System :: OS Independent
Classifier: Programming Language :: Python
Classifier: Programming Language :: Python :: 3
Classifier: Topic :: Communications
Classifier: Topic :: Internet
Classifier: Topic :: Text Processing
Classifier: Topic :: Text Processing :: Markup
Classifier: Topic :: Text Processing :: Markup :: XML
Requires-Dist: python-dateutil
